passboltapi/__init__.py
passboltapi/auth.py
passboltapi/groups.py
passboltapi/meta.py
passboltapi/resources.py
passboltapi/share.py
passboltapi/users.py
passbolt_api-0.0.5.dist-info/LICENSE
passbolt_api-0.0.5.dist-info/METADATA
passbolt_api-0.0.5.dist-info/WHEEL
passbolt_api-0.0.5.dist-info/top_level.txt
passbolt_api-0.0.5.dist-info/RECORD
