Metadata-Version: 2.1
Name: passbolt-api
Version: 0.0.5
Summary: Provides API bindings for the Passbolt API
Home-page: https://github.com/xwikisas/passbolt-api
Author: XWiki SAS Development Team
Author-email: pypi@xwiki.com
License: UNKNOWN
Platform: UNKNOWN
Classifier: Programming Language :: Python :: 3
Classifier: Intended Audience :: Developers
Classifier: License :: OSI Approved :: GNU Lesser General Public License v2 (LGPLv2)
Classifier: Operating System :: OS Independent
Requires-Dist: requests-gpgauthlib (>=0.1.2)
